skfibers/__init__.py
skfibers/fibers.py
skfibers/experiments/__init__.py
skfibers/experiments/rare_SNP_sim_simple.py
skfibers/experiments/survival_covariates_sim.py
skfibers/experiments/survival_sim_simple.py
skfibers/methods/__init__.py
skfibers/methods/bin.py
skfibers/methods/data_handling.py
skfibers/methods/population.py
skfibers/methods/util.py
scikit_fibers-2.0.0.dist-info/LICENSE
scikit_fibers-2.0.0.dist-info/METADATA
scikit_fibers-2.0.0.dist-info/WHEEL
scikit_fibers-2.0.0.dist-info/top_level.txt
scikit_fibers-2.0.0.dist-info/RECORD
