Metadata-Version: 2.1
Name: scikit-fibers
Version: 2.0.0
Summary: A Scikit Learn compatible implementation of FIBERS Algorithm
Home-page: https://github.com/UrbsLab/scikit-FIBERS
Author: Harsh Bandhey, Ryan Urbanowicz
Author-email: harsh.bandhey@cshs.org
Classifier: Programming Language :: Python :: 3
Classifier: License :: OSI Approved :: MIT License
Classifier: Operating System :: OS Independent
Requires-Python: >=3.6
License-File: LICENSE
Requires-Dist: numpy
Requires-Dist: pandas
Requires-Dist: scikit-learn
Requires-Dist: setuptools
Requires-Dist: paretoset
Requires-Dist: scipy
Requires-Dist: lifelines
Requires-Dist: skrebate (==0.7)
Requires-Dist: matplotlib
Requires-Dist: seaborn
Requires-Dist: pytest
Requires-Dist: tqdm
